LingHu/__init__.py
LingHu/dll/HDDebug64.dll
LingHu/dll/VMProtectSDK64.dll
LingHu/dll/hd64.dll
LingHu/modules/login.cpp
LingHu/modules/login.cpython-313-x86_64-linux-gnu.so
LingHu/modules/login.py
LingHu/typing/__init__.py
LingHu/typing/__init__.pyi
LingHu/typing/base.pyi
LingHu/typing/logger.pyi
LingHu/typing/login.pyi
LingHu/utils/base.cpp
LingHu/utils/base.cpython-313-x86_64-linux-gnu.so
LingHu/utils/base.py
LingHu/utils/logger.cpp
LingHu/utils/logger.cpython-313-x86_64-linux-gnu.so
LingHu/utils/logger.py
linghu-1.0.0.dist-info/METADATA
linghu-1.0.0.dist-info/WHEEL
linghu-1.0.0.dist-info/top_level.txt
linghu-1.0.0.dist-info/RECORD
