Metadata-Version: 2.4
Name: LingHu
Version: 1.0.0
Summary: LingHu - 智能化工具包
Home-page: https://github.com/linghu-team/LingHu
Author: LingHu Team
Author-email: LingHu Team <team@linghu.com>
License: MIT
Project-URL: Homepage, https://github.com/linghu-team/LingHu
Project-URL: Documentation, https://linghu.readthedocs.io
Project-URL: Repository, https://github.com/linghu-team/LingHu.git
Project-URL: Bug Tracker, https://github.com/linghu-team/LingHu/issues
Platform: any
Classifier: Development Status :: 4 - Beta
Classifier: Intended Audience :: Developers
Classifier: License :: OSI Approved :: MIT License
Classifier: Operating System :: OS Independent
Classifier: Programming Language :: Python :: 3
Classifier: Programming Language :: Python :: 3.8
Classifier: Programming Language :: Python :: 3.9
Classifier: Programming Language :: Python :: 3.10
Classifier: Programming Language :: Python :: 3.11
Classifier: Topic :: Software Development :: Libraries :: Python Modules
Classifier: Topic :: System :: Systems Administration
Requires-Python: >=3.8
Provides-Extra: dev
Requires-Dist: cython>=0.29.0; extra == "dev"
Requires-Dist: build>=0.8.0; extra == "dev"
Requires-Dist: wheel>=0.38.0; extra == "dev"
Requires-Dist: twine>=4.0.0; extra == "dev"
Provides-Extra: test
Requires-Dist: pytest>=7.0.0; extra == "test"
Requires-Dist: pytest-cov>=4.0.0; extra == "test"
Dynamic: author
Dynamic: home-page
Dynamic: platform
Dynamic: requires-python
